pbixtrans/__init__.py
pbixtrans/_version.py
pbixtrans/cli.py
pbixtrans/extraction.py
pbixtrans/translator.py
pbixtrans/layout/__init__.py
pbixtrans/layout/io.py
pbixtrans/layout/layout_translator.py
pbixtrans/layout/registry.py
pbixtrans/layout/section.py
pbixtrans/layout/visuals/__init__.py
pbixtrans/layout/visuals/actionbutton.py
pbixtrans/layout/visuals/shape.py
pbixtrans/layout/visuals/slicer.py
pbixtrans/layout/visuals/textbox.py
pbixtrans-0.1.1.dist-info/licenses/LICENSE
pbixtrans-0.1.1.dist-info/METADATA
pbixtrans-0.1.1.dist-info/WHEEL
pbixtrans-0.1.1.dist-info/entry_points.txt
pbixtrans-0.1.1.dist-info/top_level.txt
pbixtrans-0.1.1.dist-info/RECORD
