Metadata-Version: 2.4
Name: pbixtrans
Version: 0.1.1
Summary: Translate a PBIX report visuals into another language
Author-email: tbrus01 <brus.tomasz@outlook.com>
License: MIT
Project-URL: Homepage, https://github.com/tbrus/pbixtrans
Requires-Python: >=3.9
License-File: LICENSE
Requires-Dist: googletrans==4.0.0-rc1
Dynamic: license-file
